{
  "dependencies": [
    {
      "name": "@aws/pdk",
      "version": "0.23.40",
      "type": "build"
    },
    {
      "name": "@types/jest",
      "type": "build"
    },
    {
      "name": "@types/node",
      "version": "^18",
      "type": "build"
    },
    {
      "name": "constructs",
      "version": "^10.0.0",
      "type": "build"
    },
    {
      "name": "jest",
      "type": "build"
    },
    {
      "name": "jest-junit",
      "version": "^15",
      "type": "build"
    },
    {
      "name": "projen",
      "type": "build"
    },
    {
      "name": "ts-jest",
      "type": "build"
    },
    {
      "name": "typescript",
      "type": "build"
    },
    {
      "name": "@aws-crypto/sha256-browser",
      "type": "runtime"
    },
    {
      "name": "@aws-crypto/sha256-js",
      "type": "runtime"
    },
    {
      "name": "@aws-sdk/client-sts",
      "type": "runtime"
    },
    {
      "name": "@aws-sdk/core",
      "type": "runtime"
    },
    {
      "name": "@aws-sdk/credential-provider-node",
      "type": "runtime"
    },
    {
      "name": "@aws-sdk/middleware-host-header",
      "type": "runtime"
    },
    {
      "name": "@aws-sdk/middleware-logger",
      "type": "runtime"
    },
    {
      "name": "@aws-sdk/middleware-recursion-detection",
      "type": "runtime"
    },
    {
      "name": "@aws-sdk/middleware-signing",
      "type": "runtime"
    },
    {
      "name": "@aws-sdk/middleware-user-agent",
      "type": "runtime"
    },
    {
      "name": "@aws-sdk/region-config-resolver",
      "type": "runtime"
    },
    {
      "name": "@aws-sdk/types",
      "type": "runtime"
    },
    {
      "name": "@aws-sdk/util-user-agent-browser",
      "type": "runtime"
    },
    {
      "name": "@aws-sdk/util-user-agent-node",
      "type": "runtime"
    },
    {
      "name": "@smithy/config-resolver",
      "type": "runtime"
    },
    {
      "name": "@smithy/fetch-http-handler",
      "type": "runtime"
    },
    {
      "name": "@smithy/hash-node",
      "type": "runtime"
    },
    {
      "name": "@smithy/invalid-dependency",
      "type": "runtime"
    },
    {
      "name": "@smithy/middleware-content-length",
      "type": "runtime"
    },
    {
      "name": "@smithy/middleware-retry",
      "type": "runtime"
    },
    {
      "name": "@smithy/middleware-serde",
      "type": "runtime"
    },
    {
      "name": "@smithy/middleware-stack",
      "type": "runtime"
    },
    {
      "name": "@smithy/node-config-provider",
      "type": "runtime"
    },
    {
      "name": "@smithy/node-http-handler",
      "type": "runtime"
    },
    {
      "name": "@smithy/protocol-http",
      "type": "runtime"
    },
    {
      "name": "@smithy/smithy-client",
      "type": "runtime"
    },
    {
      "name": "@smithy/types",
      "type": "runtime"
    },
    {
      "name": "@smithy/url-parser",
      "type": "runtime"
    },
    {
      "name": "@smithy/util-base64",
      "type": "runtime"
    },
    {
      "name": "@smithy/util-body-length-browser",
      "type": "runtime"
    },
    {
      "name": "@smithy/util-body-length-node",
      "type": "runtime"
    },
    {
      "name": "@smithy/util-defaults-mode-browser",
      "type": "runtime"
    },
    {
      "name": "@smithy/util-defaults-mode-node",
      "type": "runtime"
    },
    {
      "name": "@smithy/util-retry",
      "type": "runtime"
    },
    {
      "name": "@smithy/util-utf8",
      "type": "runtime"
    },
    {
      "name": "tslib",
      "type": "runtime"
    },
    {
      "name": "@types/jest",
      "type": "test"
    },
    {
      "name": "jest",
      "type": "test"
    },
    {
      "name": "ts-jest",
      "type": "test"
    }
  ],
  "//": "~~ Generated by projen. To modify, edit .projenrc.js and run \"npx projen\"."
}
